<?xml version="1.0"?>
<odoo>

    <!-- Sale order form lines -->
    <record id="js_addons_view_order_form" model="ir.ui.view">
        <field name="name">sale.order.form.inherit</field>
        <field name="model">sale.order</field>
        <field name="inherit_id" ref="custom_sale_order_variant_mgmt.sale_order_variants" />
        <field name="priority">20</field>
        <field name="arch" type="xml">
            <xpath expr="//field[@name='template_lines']/tree" position="inside">
                <field name="discontinued_line" invisible="1" />
            </xpath>

            <xpath expr="//field[@name='template_lines']/tree" position="attributes">
                <attribute name="decoration-muted">discontinued_line == True</attribute>
                <attribute name="decoration-it">discontinued_line == True</attribute>
            </xpath>

            <xpath expr="//field[@name='template_lines']/tree" position="before">
                <p class="text-danger">Las líneas grises y en cursiva indican que el producto está descatalogado (o una de sus variantes, ver líneas)</p>
            </xpath>
        </field>
    </record>

    <!-- Sale order lines detail -->
    <record id="js_addons_view_order_lines" model="ir.ui.view">
        <field name="name">sale.order.line.tree.inherit</field>
        <field name="model">sale.order.line</field>
        <field name="inherit_id" ref="custom_sale_order_variant_mgmt.sale_order_line_custom_tree" />
        <field name="priority">20</field>
        <field name="arch" type="xml">
            <xpath expr="//tree" position="inside">
                <field name="discontinued_line" invisible="1" />
            </xpath>

            <xpath expr="//tree" position="attributes">
                <attribute name="decoration-muted">discontinued_line == True</attribute>
                <attribute name="decoration-it">discontinued_line == True</attribute>
            </xpath>
        </field>
    </record>

</odoo>
