<?xml version="1.0" encoding="utf-8"?>
<odoo>

    <record id="view_order_product_search_attributes" model="ir.ui.view">
        <field name="name">sale.report.attributes.search</field>
        <field name="model">sale.report</field>
        <field name="inherit_id" ref="sale.view_order_product_search"/>
        <field name="arch" type="xml">
            <field name="user_id" position="after">
                <separator/>
                <field name="color_id"/>
                <field name="size_id"/>
            </field>
        </field>
    </record>

</odoo>
